gamlogger/__init__.py
glogger/__init__.py
gamlogger-0.9.0.dist-info/AUTHORS
gamlogger-0.9.0.dist-info/LICENSE
gamlogger-0.9.0.dist-info/METADATA
gamlogger-0.9.0.dist-info/WHEEL
gamlogger-0.9.0.dist-info/top_level.txt
gamlogger-0.9.0.dist-info/RECORD
